AUTHORS
CONTRIBUTING.rst
ChangeLog
LICENSE
README.rst
_config.yml
model.test.json
requirements.txt
setup.cfg
setup.py
test-requirements.txt
tox.ini
upload.sh
sphinxcontrib/RestAPIContext.py
sphinxcontrib/SphinxRest.py
sphinxcontrib/__init__.py
sphinxcontrib/api.jinja2.1.txt
sphinxcontrib/templates/create.jinja2
sphinxcontrib/templates/delete.jinja2
sphinxcontrib/templates/list.jinja2
sphinxcontrib/templates/read.jinja2
sphinxcontrib/templates/update.jinja2
sphinxcontrib_sphinx_rest_api_doc.egg-info/PKG-INFO
sphinxcontrib_sphinx_rest_api_doc.egg-info/SOURCES.txt
sphinxcontrib_sphinx_rest_api_doc.egg-info/dependency_links.txt
sphinxcontrib_sphinx_rest_api_doc.egg-info/namespace_packages.txt
sphinxcontrib_sphinx_rest_api_doc.egg-info/not-zip-safe
sphinxcontrib_sphinx_rest_api_doc.egg-info/pbr.json
sphinxcontrib_sphinx_rest_api_doc.egg-info/requires.txt
sphinxcontrib_sphinx_rest_api_doc.egg-info/top_level.txt
tests/conftest.py