Metadata-Version: 1.2
Name: sphinxcontrib-sphinx-rest-api-doc
Version: 0.0.33.dev4
Summary: a tools for sphinx gen doc from rest api
Home-page: https://github.com/yishenggudou/sphinx-rest-api-doc
Author: yishenggudou
Author-email: yishenggudou@gmail.com
License: BSD 2
Platform: any
Classifier: Development Status :: 3 - Alpha
Classifier: Environment :: Console
Classifier: Framework :: Sphinx :: Extension
Classifier: Intended Audience :: Developers
Classifier: License :: OSI Approved :: Apache Software License
Classifier: Operating System :: OS Independent
Classifier: Programming Language :: Python
Classifier: Programming Language :: Python :: 3
Classifier: Programming Language :: Python :: 3.5
Classifier: Topic :: Documentation
Classifier: Topic :: Utilities
Requires-Python: >3.0
